stang_tz_pdf2word/__init__.py
stang_tz_pdf2word-0.1.0.dist-info/METADATA
stang_tz_pdf2word-0.1.0.dist-info/WHEEL
stang_tz_pdf2word-0.1.0.dist-info/entry_points.txt
stang_tz_pdf2word-0.1.0.dist-info/RECORD
