Metadata-Version: 2.4
Name: stang-tz-pdf2word
Version: 0.1.0
Summary: Add your description here
Author-email: tan_zhuo <14414039+zhuo_tan@user.noreply.gitee.com>
Requires-Python: >=3.12
Requires-Dist: mcp[cli]>=1.13.0
Requires-Dist: requests>=2.32.5
